poetrypractice/__init__.py
poetrypractice-0.1.0.dist-info/METADATA
poetrypractice-0.1.0.dist-info/WHEEL
poetrypractice-0.1.0.dist-info/RECORD
