Metadata-Version: 2.3
Name: poetrypractice
Version: 0.1.0
Summary: first potrey practice project
Author: Your Name
Author-email: you@example.com
Requires-Python: >=3.12
Classifier: Programming Language :: Python :: 3
Classifier: Programming Language :: Python :: 3.12
Classifier: Programming Language :: Python :: 3.13
Requires-Dist: allure-pytest (>=2.14.2,<3.0.0)
Requires-Dist: pydantic (>=2.11.4,<3.0.0)
Requires-Dist: pytest (>=8.3.5,<9.0.0)
Requires-Dist: requests (>=2.32.3,<3.0.0)
